jdcal.py
jdcal-1.4.dist-info/DESCRIPTION.rst
jdcal-1.4.dist-info/LICENSE.txt
jdcal-1.4.dist-info/METADATA
jdcal-1.4.dist-info/RECORD
jdcal-1.4.dist-info/WHEEL
jdcal-1.4.dist-info/metadata.json
jdcal-1.4.dist-info/top_level.txt
